README.md
setup.py
genomon_expression/__init__.py
genomon_expression/parser.py
genomon_expression/run.py
genomon_expression/utils.py
genomon_expression.egg-info/PKG-INFO
genomon_expression.egg-info/SOURCES.txt
genomon_expression.egg-info/dependency_links.txt
genomon_expression.egg-info/entry_points.txt
genomon_expression.egg-info/top_level.txt