Metadata-Version: 1.1
Name: genomon-expression
Version: 0.4.0
Summary: Python tools for calculating fkpm values from RNA-seq
Home-page: https://github.com/Genomon-Project/GenomonExpression.git
Author: Yuichi Shiraishi
Author-email: friend1ws@gamil.com
License: GPLv3
Platform: UNKNOWN
Classifier: Development Status :: 4 - Beta
Classifier: Intended Audience :: Science/Research
Classifier: License :: OSI Approved :: GNU General Public License v3 (GPLv3)
Classifier: Operating System :: Unix
Classifier: Programming Language :: Python :: 2.7
Classifier: Topic :: Scientific/Engineering :: Bio-Informatics
